mrtommy/__init__.py
mrtommy/__main__.py
mrtommy/benchmark.py
mrtommy/constants.py
mrtommy/geometry.py
mrtommy/scene.py
mrtommy/solver.py
mrtommy/utilities.py
mrtommy/solvers/__init__.py
mrtommy/solvers/drrt.py
mrtommy/solvers/drrt_star.py
mrtommy/solvers/hgraph.py
mrtommy/solvers/prm.py
mrtommy/solvers/rrt.py
mrtommy/solvers/rrt_star.py
mrtommy-0.1.1.dist-info/METADATA
mrtommy-0.1.1.dist-info/WHEEL
mrtommy-0.1.1.dist-info/RECORD
