Metadata-Version: 2.3
Name: mrtommy
Version: 0.1.1
Summary: Multi-Robot Trajectory Organization and Motion Modeling Yard
Project-URL: Repository, https://github.com/noamzaks/mrtommy
Author-email: Noam Zaks <imnoamzaks@gmail.com>
License-Expression: MIT
Requires-Python: >=3.8
Requires-Dist: matplotlib>=3.9.0
Requires-Dist: networkx>=3.3
Requires-Dist: numpy>=1.26.4
Requires-Dist: pandas>=2.2.2
Requires-Dist: tqdm>=4.66.4
